xgp_reccomender/Game.py
xgp_reccomender/__init__.py
xgp_reccomender/main.py
xgp_reccomender/xgp_reccomender.py
xgp_reccomender-2.0.1.dist-info/LICENSE.txt
xgp_reccomender-2.0.1.dist-info/METADATA
xgp_reccomender-2.0.1.dist-info/WHEEL
xgp_reccomender-2.0.1.dist-info/entry_points.txt
xgp_reccomender-2.0.1.dist-info/top_level.txt
xgp_reccomender-2.0.1.dist-info/RECORD
