Metadata-Version: 2.1
Name: xgp-reccomender
Version: 2.0.1
Summary: App searches for avaiable Xbox Game Pass games and helps to choose what to play next.
Home-page: https://github.com/aowczarek618/xgp-reccomender
License: UNKNOWN
Project-URL: Bug Reports, https://github.com/aowczarek618/xgp-reccomender/issues
Project-URL: Source, https://github.com/aowczarek618/xgp-reccomender
Platform: UNKNOWN
Requires-Python: >=3.5, <4
Requires-Dist: requests
Requires-Dist: beautifulsoup4
Requires-Dist: pandas
